mistdata/DUTLNA.py
mistdata/DUTRecIn.py
mistdata/LSTBinnedSpectra.py
mistdata/MISTData.py
mistdata/MISTData_methods/plotting_raw.py
mistdata/Spectrum.py
mistdata/Thermistors.py
mistdata/__init__.py
mistdata/plotting.py
mistdata/utils.py
mistdata-0.1.2.dist-info/LICENSE
mistdata-0.1.2.dist-info/METADATA
mistdata-0.1.2.dist-info/WHEEL
mistdata-0.1.2.dist-info/RECORD
